CNSeq2TimeSpan/LunarSolarConverter.py
CNSeq2TimeSpan/RangeTimeEnum.py
CNSeq2TimeSpan/StringPreHandler.py
CNSeq2TimeSpan/Test.py
CNSeq2TimeSpan/TimeNormalizer.py
CNSeq2TimeSpan/TimePoint.py
CNSeq2TimeSpan/TimeUnit.py
CNSeq2TimeSpan/__init__.py
CNSeq2TimeSpan/__version__.py
CNSeq2TimeSpan/core.py
CNSeq2TimeSpan/resource/__init__.py
CNSeq2TimeSpan-0.1.9.dist-info/LICENSE
CNSeq2TimeSpan-0.1.9.dist-info/METADATA
CNSeq2TimeSpan-0.1.9.dist-info/WHEEL
CNSeq2TimeSpan-0.1.9.dist-info/top_level.txt
CNSeq2TimeSpan-0.1.9.dist-info/RECORD
