Metadata-Version: 2.1
Name: CNSeq2TimeSpan
Version: 0.1.9
Summary: This is a tool for converting chinese time phrases into time spans.
Home-page: https://github.com/QixinLi/Time_NLP
Author: Qixin Li
Author-email: qixinli1997@hotmail.com
License: MIT
Platform: UNKNOWN
Classifier: License :: OSI Approved :: MIT License
Classifier: Programming Language :: Python
Classifier: Programming Language :: Python :: 3
Classifier: Programming Language :: Python :: 3.6
Classifier: Programming Language :: Python :: Implementation :: CPython
Classifier: Programming Language :: Python :: Implementation :: PyPy
Requires-Python: >=3.5.0
Requires-Dist: arrow (==0.13.1)
Requires-Dist: regex (>2017)
